gitir_downloader/__init__.py
gitir_downloader/downloader.py
gitir_downloader/main.py
gitir_downloader/parser.py
gitir_downloader/utils/__init__.py
gitir_downloader/utils/tidy_names.py
gitir_download-1.0.1.dist-info/METADATA
gitir_download-1.0.1.dist-info/WHEEL
gitir_download-1.0.1.dist-info/entry_points.txt
gitir_download-1.0.1.dist-info/top_level.txt
gitir_download-1.0.1.dist-info/RECORD
