Metadata-Version: 2.1
Name: gitir-download
Version: 1.0.1
Summary: Download videos from scattered links of git.ir
Home-page: https://github.com/yankeexe/git.ir_downloader
Author: Yankee Maharjan
Author-email: yankee.exe@gmail.com
License: MIT
Platform: UNKNOWN
Classifier: Programming Language :: Python :: 3.6
Classifier: Programming Language :: Python :: 3.8
Classifier: Operating System :: OS Independent
Classifier: Development Status :: 1 - Planning
Classifier: License :: OSI Approved :: MIT License
Requires-Dist: beautifulsoup4
Requires-Dist: halo
Requires-Dist: requests
Requires-Dist: tqdm
Provides-Extra: dev
Requires-Dist: pytest (<=4.*) ; extra == 'dev'
Requires-Dist: black (<=19.10b0) ; extra == 'dev'
